gyakuhonyaku/gyakuhonyaku.py
gyakuhonyaku-1.0.0.dist-info/METADATA
gyakuhonyaku-1.0.0.dist-info/WHEEL
gyakuhonyaku-1.0.0.dist-info/top_level.txt
gyakuhonyaku-1.0.0.dist-info/RECORD
