Metadata-Version: 2.1
Name: gyakuhonyaku
Version: 1.0.0
Summary: Use google translate ambiguity to make funny sentence
Home-page: https://github.com/Nagatochyan/gyakuhonyaku-module
Author: Nagato
Author-email: projectnaganegi@gmail.com
License: MIT
Keywords: gyakuhonyaku gyakutranslate
Classifier: License :: OSI Approved :: MIT License
Classifier: Programming Language :: Python :: 3.6
Requires-Dist: googletrans (==4.0.0-rc1)
